genotype_variants/__init__.py
genotype_variants/cli.py
genotype_variants/create_all_maf_dataframe.py
genotype_variants/create_duplex_simplex_dataframe.py
genotype_variants/generate_summary_field.py
genotype_variants/genotype_variants.py
genotype_variants/run_cmd.py
genotype_variants/commands/__init__.py
genotype_variants/commands/small_variants.py
genotype_variants-0.3.10.dist-info/licenses/AUTHORS.rst
genotype_variants-0.3.10.dist-info/licenses/LICENSE
genotype_variants-0.3.10.dist-info/METADATA
genotype_variants-0.3.10.dist-info/WHEEL
genotype_variants-0.3.10.dist-info/entry_points.txt
genotype_variants-0.3.10.dist-info/top_level.txt
genotype_variants-0.3.10.dist-info/RECORD
